soap/__init__.py
soap/announce.py
soap/announcer.py
soap_altair_announce-0.0.2.dist-info/METADATA
soap_altair_announce-0.0.2.dist-info/WHEEL
soap_altair_announce-0.0.2.dist-info/top_level.txt
soap_altair_announce-0.0.2.dist-info/RECORD
